odoo8_addon_analytic_department-8.0.1.0.0-py2.7-nspkg.pth
odoo_addons/analytic_department/analytic_view.xml
odoo_addons/analytic_department/__openerp__.py
odoo_addons/analytic_department/__init__.py
odoo_addons/analytic_department/LICENSE
odoo_addons/analytic_department/i18n/pt.po
odoo_addons/analytic_department/i18n/es.po
odoo_addons/analytic_department/i18n/analytic_department.pot
odoo8_addon_analytic_department-8.0.1.0.0.dist-info/top_level.txt
odoo8_addon_analytic_department-8.0.1.0.0.dist-info/WHEEL
odoo8_addon_analytic_department-8.0.1.0.0.dist-info/RECORD
odoo8_addon_analytic_department-8.0.1.0.0.dist-info/metadata.json
odoo8_addon_analytic_department-8.0.1.0.0.dist-info/DESCRIPTION.rst
odoo8_addon_analytic_department-8.0.1.0.0.dist-info/METADATA
odoo8_addon_analytic_department-8.0.1.0.0.dist-info/namespace_packages.txt
